LICENSE.TXT
README.md
setup.cfg
setup.py
nwgraph/__init__.py
nwgraph/logger.py
nwgraph.egg-info/PKG-INFO
nwgraph.egg-info/SOURCES.txt
nwgraph.egg-info/dependency_links.txt
nwgraph.egg-info/requires.txt
nwgraph.egg-info/top_level.txt
nwgraph/graph/__init__.py
nwgraph/graph/bipartite_graph.py
nwgraph/graph/graph.py
nwgraph/graph/internal.py
nwgraph/graph/nodes_state.py
nwgraph/graph/edge/__init__.py
nwgraph/graph/edge/edge.py
nwgraph/graph/node/__init__.py
nwgraph/graph/node/dim_node.py
nwgraph/graph/node/node.py
nwgraph/layers/__init__.py
nwgraph/layers/ensemble_mp.py
nwgraph/layers/gcn.py
nwgraph/layers/pathway_list_mp/__init__.py
nwgraph/layers/pathway_list_mp/pathway_list_mp.py
nwgraph/layers/pathway_list_mp/utils.py
nwgraph/message_passing/__init__.py
nwgraph/message_passing/message_passing.py
nwgraph/message_passing/pathway_list_message_passing.py
nwgraph/pathway/__init__.py
nwgraph/pathway/converging_pathways.py
nwgraph/pathway/pathway.py
nwgraph/pathway/pathway_builder.py
nwgraph/pathway/pathway_list.py
nwgraph/utils/__init__.py
nwgraph/utils/torch.py
nwgraph/utils/types.py
nwgraph/utils/utils.py