Metadata-Version: 2.1
Name: nwgraph
Version: 3.0.2
Summary: Neural Wrappers Graph library
Home-page: https://gitlab.com/neuralwrappers/nwgraph
License: WTFPL
Requires-Python: >=3.10
License-File: LICENSE.TXT
Requires-Dist: torch>=2.5.1
Requires-Dist: tqdm==4.67.1
Requires-Dist: overrides==7.7.0
Requires-Dist: graphviz==0.20.1
Requires-Dist: colorama==0.4.6
Requires-Dist: lovely_tensors==0.1.17
Requires-Dist: numpy==1.26.4
Requires-Dist: loggez==0.4.2
